{
  "version": "6",
  "dialect": "sqlite",
  "id": "8afbf261-a066-440e-93ae-8da6acc5354c",
  "prevId": "cb616729-fbff-4573-ad26-2bad022df348",
  "tables": {
    "waitlist": {
      "name": "waitlist",
      "columns": {
        "id": {
          "name": "id",
          "type": "integer",
          "primaryKey": true,
          "notNull": true,
          "autoincrement": true
        },
        "email": {
          "name": "email",
          "type": "text",
          "primaryKey": false,
          "notNull": true,
          "autoincrement": false
        },
        "verified_at": {
          "name": "verified_at",
          "type": "integer",
          "primaryKey": false,
          "notNull": false,
          "autoincrement": false
        },
        "created_at": {
          "name": "created_at",
          "type": "integer",
          "primaryKey": false,
          "notNull": true,
          "autoincrement": false
        }
      },
      "indexes": {
        "waitlist_email_unique": {
          "name": "waitlist_email_unique",
          "columns": [
            "email"
          ],
          "isUnique": true
        },
        "email_idx": {
          "name": "email_idx",
          "columns": [
            "email"
          ],
          "isUnique": true
        }
      },
      "foreignKeys": {},
      "compositePrimaryKeys": {},
      "uniqueConstraints": {}
    }
  },
  "enums": {},
  "_meta": {
    "schemas": {},
    "tables": {},
    "columns": {}
  },
  "internal": {
    "indexes": {}
  }
}